squeezebox_cli/__init__.py
squeezebox_cli/core/__init__.py
squeezebox_cli/core/protocol.py
squeezebox_cli/database/__init__.py
squeezebox_cli/database/commands.py
squeezebox_cli/display/__init__.py
squeezebox_cli/display/monitor.py
squeezebox_cli/display/status.py
squeezebox_cli/player/__init__.py
squeezebox_cli/player/commands.py
squeezebox_cli/tests/__init__.py
squeezebox_cli/ui/__init__.py
squeezebox_cli/ui/main.py
tests/__init__.py
tests/conftest.py
tests/helpers.py
tests/test_core_protocol.py
tests/test_database.py
tests/test_display.py
tests/test_player_commands.py
tests/test_ui_main.py
squeezebox_cli-0.2.3.dist-info/METADATA
squeezebox_cli-0.2.3.dist-info/WHEEL
squeezebox_cli-0.2.3.dist-info/entry_points.txt
squeezebox_cli-0.2.3.dist-info/top_level.txt
squeezebox_cli-0.2.3.dist-info/zip-safe
squeezebox_cli-0.2.3.dist-info/RECORD
