Metadata-Version: 2.1
Name: squeezebox-cli
Version: 0.2.3
Summary: A command line interface to control your Squeezebox
Home-page: https://gitlab.com/OldIronHorse/squeezebox-cli
Author: Simon Redding
Author-email: s1m0n.r3dd1ng@gmail.com
License: GPLv3
Keywords: media player,squeezebox,multiroom audio
Classifier: License :: OSI Approved :: GNU General Public License v3 (GPLv3)
Classifier: Programming Language :: Python :: 3
Requires-Python: >=3.11
Requires-Dist: click
Requires-Dist: tabulate
Requires-Dist: dateparser
Requires-Dist: requests
Provides-Extra: dev
Requires-Dist: flake8 ; extra == 'dev'
Requires-Dist: bandit ; extra == 'dev'
Requires-Dist: pytest ; extra == 'dev'
Requires-Dist: pytest-cov ; extra == 'dev'
Requires-Dist: pytest-watch ; extra == 'dev'
Requires-Dist: pytest-mock ; extra == 'dev'
